pyjstat/__init__.py
pyjstat/pyjstat.py
pyjstat/test/__init__.py
pyjstat/test/test.py
pyjstat-2.0.0.dist-info/LICENSE.txt
pyjstat-2.0.0.dist-info/METADATA
pyjstat-2.0.0.dist-info/WHEEL
pyjstat-2.0.0.dist-info/top_level.txt
pyjstat-2.0.0.dist-info/RECORD
