Metadata-Version: 2.1
Name: pyjstat
Version: 2.0.0
Summary: Library to handle JSON-stat data in python using pandas DataFrames.
Home-page: https://github.com/predicador37/pyjstat
Author: Miguel Expósito Martín
Author-email: miguel.exposito@gmail.com
License: Apache License 2.0
Keywords: json-stat,json,statistics,dataframe,converter
Platform: UNKNOWN
Classifier: Development Status :: 4 - Beta
Classifier: Environment :: Console
Classifier: Intended Audience :: Developers
Classifier: Intended Audience :: Science/Research
Classifier: License :: OSI Approved :: Apache Software License
Classifier: Operating System :: MacOS :: MacOS X
Classifier: Operating System :: Microsoft :: Windows
Classifier: Operating System :: POSIX
Classifier: Programming Language :: Python
Classifier: Topic :: Scientific/Engineering :: Information Analysis
Classifier: Topic :: Software Development :: Libraries
Requires-Dist: pandas
Requires-Dist: requests
